gdbcore/__init__.py
gdbcore/apoc_load_queries.py
gdbcore/csv_formatter.py
gdbcore/cypher_load_queries.py
gdbcore/dump_to_nelists.py
gdbcore/helpers/__init__.py
gdbcore/helpers/utils.py
gdbcore/helpers/utils_cypher.py
gdbcore/helpers/utils_gt.py
gdbcore/helpers/utils_nelist.py
gdbcore/helpers/utils_neo4j.py
gdbcore/helpers/utils_nx.py
gdbcore/helpers/utils_obonet.py
gdbcore/list_builder.py
gdbcore/neo4j_bulk_import.py
gdbcore/nx_builder.py
gdbcore/obo_to_csv.py
gdbcore-0.1.1.dist-info/METADATA
gdbcore-0.1.1.dist-info/WHEEL
gdbcore-0.1.1.dist-info/RECORD
